contracts/__init__.py
contracts/backported.py
contracts/docstring_parsing.py
contracts/enabling.py
contracts/inspection.py
contracts/interface.py
contracts/main.py
contracts/main_actual.py
contracts/metaclass.py
contracts/pyparsing_utils.py
contracts/syntax.py
contracts/utils.py
contracts/library/__init__.py
contracts/library/arithmetic.py
contracts/library/array.py
contracts/library/array_ops.py
contracts/library/attributes.py
contracts/library/comparison.py
contracts/library/compositions.py
contracts/library/dicts.py
contracts/library/dummy.py
contracts/library/extensions.py
contracts/library/files.py
contracts/library/isinstance_imp.py
contracts/library/lists.py
contracts/library/map.py
contracts/library/miscellaneous_aliases.py
contracts/library/scoped_variables.py
contracts/library/separate_context.py
contracts/library/seq.py
contracts/library/sets.py
contracts/library/simple_values.py
contracts/library/strings.py
contracts/library/suggester.py
contracts/library/tuple.py
contracts/library/types_misc.py
contracts/library/variables.py
contracts/useful_contracts/__init__.py
contracts/useful_contracts/numbers.py
contracts/useful_contracts/numpy_specific.py
pytreaty-2019.1b5.dist-info/METADATA
pytreaty-2019.1b5.dist-info/RECORD
pytreaty-2019.1b5.dist-info/WHEEL
pytreaty-2019.1b5.dist-info/top_level.txt
