Metadata-Version: 2.1
Name: pytreaty
Version: 2019.1b5
Summary: PyTreaty is a hard fork of the PyContracts library from Andrea Censi. This fork has been updated to allow multiple contract definitions on a function, as well as removing Python 2.x support and other updates.
Home-page: http://github.com/bluecoveltd/contracts
Author: BlueCove Developers
License: LGPL
Download-URL: http://github.com/bluecoveltd/contracts/tarball/2019.1b5
Keywords: type checking,value checking,contracts
Platform: UNKNOWN
Classifier: Development Status :: 4 - Beta
Classifier: Intended Audience :: Developers
Classifier: License :: OSI Approved :: GNU Library or Lesser General Public License (LGPL)
Classifier: Topic :: Software Development :: Quality Assurance
Classifier: Topic :: Software Development :: Documentation
Classifier: Topic :: Software Development :: Testing
Requires-Dist: pyparsing
Requires-Dist: decorator
Requires-Dist: six
Requires-Dist: pandas
Requires-Dist: numpy
